{
"meta":{"test_sets":[],"test_metrics":[],"learn_metrics":[{"best_value":"Min","name":"Logloss"}],"launch_mode":"Train","parameters":"","iteration_count":300,"learn_sets":["learn"],"name":"experiment"},
"iterations":[
{"learn":[0.61185524],"iteration":0,"passed_time":0.008263236649,"remaining_time":2.470707758},
{"learn":[0.5603067451],"iteration":1,"passed_time":0.01411415603,"remaining_time":2.103009248},
{"learn":[0.5163563358],"iteration":2,"passed_time":0.01946120376,"remaining_time":1.926659172},
{"learn":[0.472929805],"iteration":3,"passed_time":0.02409692289,"remaining_time":1.783172294},
{"learn":[0.4359597355],"iteration":4,"passed_time":0.02942638741,"remaining_time":1.736156857},
{"learn":[0.4089677878],"iteration":5,"passed_time":0.03424748031,"remaining_time":1.678126535},
{"learn":[0.3793368121],"iteration":6,"passed_time":0.03879715835,"remaining_time":1.623938199},
{"learn":[0.3546341961],"iteration":7,"passed_time":0.04377850018,"remaining_time":1.597915257},
{"learn":[0.3313022816],"iteration":8,"passed_time":0.0486768009,"remaining_time":1.573883229},
{"learn":[0.309959589],"iteration":9,"passed_time":0.05392143265,"remaining_time":1.563721547},
{"learn":[0.2956274422],"iteration":10,"passed_time":0.05850540213,"remaining_time":1.537096474},
{"learn":[0.281630642],"iteration":11,"passed_time":0.06377453371,"remaining_time":1.530588809},
{"learn":[0.2678011505],"iteration":12,"passed_time":0.06959086999,"remaining_time":1.536352284},
{"learn":[0.2553733789],"iteration":13,"passed_time":0.07505666693,"remaining_time":1.533300482},
{"learn":[0.2453833924],"iteration":14,"passed_time":0.08029134041,"remaining_time":1.525535468},
{"learn":[0.2329914183],"iteration":15,"passed_time":0.08498176751,"remaining_time":1.508426373},
{"learn":[0.2243469126],"iteration":16,"passed_time":0.08995410941,"remaining_time":1.497471351},
{"learn":[0.2190165814],"iteration":17,"passed_time":0.09503478391,"remaining_time":1.488878281},
{"learn":[0.2123883125],"iteration":18,"passed_time":0.09986121011,"remaining_time":1.476894739},
{"learn":[0.2070506885],"iteration":19,"passed_time":0.1052827573,"remaining_time":1.473958603},
{"learn":[0.2019688463],"iteration":20,"passed_time":0.1103291404,"remaining_time":1.465801437},
{"learn":[0.1960968482],"iteration":21,"passed_time":0.1150117759,"remaining_time":1.453330623},
{"learn":[0.1901125102],"iteration":22,"passed_time":0.1203698652,"remaining_time":1.449671855},
{"learn":[0.1857744014],"iteration":23,"passed_time":0.1254745812,"remaining_time":1.442957684},
{"learn":[0.1803834159],"iteration":24,"passed_time":0.1301103837,"remaining_time":1.431214221},
{"learn":[0.1766872625],"iteration":25,"passed_time":0.1349069768,"remaining_time":1.421711986},
{"learn":[0.1723327061],"iteration":26,"passed_time":0.1397442362,"remaining_time":1.4129695},
{"learn":[0.1688826314],"iteration":27,"passed_time":0.1445842457,"remaining_time":1.404532672},
{"learn":[0.1659854011],"iteration":28,"passed_time":0.1490308411,"remaining_time":1.392667515},
{"learn":[0.1636509627],"iteration":29,"passed_time":0.1542268898,"remaining_time":1.388042008},
{"learn":[0.1609389421],"iteration":30,"passed_time":0.1587535263,"remaining_time":1.377570922},
{"learn":[0.1590806894],"iteration":31,"passed_time":0.1632897878,"remaining_time":1.367551973},
{"learn":[0.1572115346],"iteration":32,"passed_time":0.1676035924,"remaining_time":1.356065429},
{"learn":[0.1547371965],"iteration":33,"passed_time":0.173014098,"remaining_time":1.353580885},
{"learn":[0.1528711047],"iteration":34,"passed_time":0.1779603568,"remaining_time":1.34741413},
{"learn":[0.1508443942],"iteration":35,"passed_time":0.1824248271,"remaining_time":1.337782065},
{"learn":[0.1486507736],"iteration":36,"passed_time":0.1877682915,"remaining_time":1.334677315},
{"learn":[0.1467091549],"iteration":37,"passed_time":0.1923931774,"remaining_time":1.326500328},
{"learn":[0.1451071213],"iteration":38,"passed_time":0.1973267278,"remaining_time":1.320571179},
{"learn":[0.1427462103],"iteration":39,"passed_time":0.2022379868,"remaining_time":1.314546914},
{"learn":[0.1407283219],"iteration":40,"passed_time":0.2061315442,"remaining_time":1.302148048},
{"learn":[0.1390192491],"iteration":41,"passed_time":0.2097965198,"remaining_time":1.28875005},
{"learn":[0.1369294501],"iteration":42,"passed_time":0.214223282,"remaining_time":1.280357755},
{"learn":[0.1362085473],"iteration":43,"passed_time":0.2185225867,"remaining_time":1.271404141},
{"learn":[0.1348606269],"iteration":44,"passed_time":0.2236939273,"remaining_time":1.267598921},
{"learn":[0.1335154079],"iteration":45,"passed_time":0.2298228448,"remaining_time":1.269021795},
{"learn":[0.1326481203],"iteration":46,"passed_time":0.2342191905,"remaining_time":1.260796919},
{"learn":[0.1314274187],"iteration":47,"passed_time":0.2386135779,"remaining_time":1.252721284},
{"learn":[0.1303469625],"iteration":48,"passed_time":0.2426450928,"remaining_time":1.242937108},
{"learn":[0.12968527],"iteration":49,"passed_time":0.2483359715,"remaining_time":1.241679858},
{"learn":[0.1288455441],"iteration":50,"passed_time":0.2561955442,"remaining_time":1.250837069},
{"learn":[0.1280449169],"iteration":51,"passed_time":0.2601415596,"remaining_time":1.24067513},
{"learn":[0.1272571068],"iteration":52,"passed_time":0.2642107825,"remaining_time":1.231321949},
{"learn":[0.1266175209],"iteration":53,"passed_time":0.2684325877,"remaining_time":1.222859566},
{"learn":[0.1259639806],"iteration":54,"passed_time":0.2726624762,"remaining_time":1.214587394},
{"learn":[0.1251733908],"iteration":55,"passed_time":0.2767941987,"remaining_time":1.206031866},
{"learn":[0.1237024136],"iteration":56,"passed_time":0.2806960478,"remaining_time":1.196651572},
{"learn":[0.1230476158],"iteration":57,"passed_time":0.2845753136,"remaining_time":1.187365964},
{"learn":[0.1226580734],"iteration":58,"passed_time":0.2887240776,"remaining_time":1.179364453},
{"learn":[0.1220349497],"iteration":59,"passed_time":0.292567552,"remaining_time":1.170270208},
{"learn":[0.1216141596],"iteration":60,"passed_time":0.2966902746,"remaining_time":1.162442223},
{"learn":[0.121014648],"iteration":61,"passed_time":0.3013746601,"remaining_time":1.156889824},
{"learn":[0.1201340542],"iteration":62,"passed_time":0.305337467,"remaining_time":1.148650471},
{"learn":[0.119707391],"iteration":63,"passed_time":0.3094647729,"remaining_time":1.14115135},
{"learn":[0.1188427388],"iteration":64,"passed_time":0.3134542463,"remaining_time":1.13325766},
{"learn":[0.1184178926],"iteration":65,"passed_time":0.3183453387,"remaining_time":1.128678928},
{"learn":[0.1181228037],"iteration":66,"passed_time":0.3224189783,"remaining_time":1.121248089},
{"learn":[0.1177378722],"iteration":67,"passed_time":0.3266382002,"remaining_time":1.114412683},
{"learn":[0.1172947729],"iteration":68,"passed_time":0.3322662044,"remaining_time":1.112369467},
{"learn":[0.1165974085],"iteration":69,"passed_time":0.3360965539,"remaining_time":1.104317248},
{"learn":[0.1160532598],"iteration":70,"passed_time":0.3399710281,"remaining_time":1.096526274},
{"learn":[0.1156630866],"iteration":71,"passed_time":0.3438642522,"remaining_time":1.088903465},
{"learn":[0.1152311642],"iteration":72,"passed_time":0.3476677685,"remaining_time":1.081103883},
{"learn":[0.1146909581],"iteration":73,"passed_time":0.352006448,"remaining_time":1.075046719},
{"learn":[0.1144388664],"iteration":74,"passed_time":0.3558525473,"remaining_time":1.067557642},
{"learn":[0.11395152],"iteration":75,"passed_time":0.3596815219,"remaining_time":1.060113959},
{"learn":[0.1136012907],"iteration":76,"passed_time":0.3636265789,"remaining_time":1.053100352},
{"learn":[0.1131716045],"iteration":77,"passed_time":0.3683631724,"remaining_time":1.04841826},
{"learn":[0.112950843],"iteration":78,"passed_time":0.3723319376,"remaining_time":1.041586813},
{"learn":[0.1127456811],"iteration":79,"passed_time":0.3764689934,"remaining_time":1.035289732},
{"learn":[0.1124817074],"iteration":80,"passed_time":0.3803626342,"remaining_time":1.028387863},
{"learn":[0.1121711986],"iteration":81,"passed_time":0.3840811094,"remaining_time":1.021093681},
{"learn":[0.1119485842],"iteration":82,"passed_time":0.3878961673,"remaining_time":1.014138172},
{"learn":[0.1115089789],"iteration":83,"passed_time":0.3919861401,"remaining_time":1.00796436},
{"learn":[0.1112645863],"iteration":84,"passed_time":0.3962669033,"remaining_time":1.002322167},
{"learn":[0.1107765342],"iteration":85,"passed_time":0.4005832912,"remaining_time":0.9968002827},
{"learn":[0.1105127093],"iteration":86,"passed_time":0.4044778486,"remaining_time":0.9902733535},
{"learn":[0.1103578952],"iteration":87,"passed_time":0.4085844879,"remaining_time":0.9843171754},
{"learn":[0.1100943654],"iteration":88,"passed_time":0.4141385759,"remaining_time":0.9818341519},
{"learn":[0.1096979295],"iteration":89,"passed_time":0.4187178788,"remaining_time":0.9770083838},
{"learn":[0.1094629775],"iteration":90,"passed_time":0.4225798531,"remaining_time":0.9705405417},
{"learn":[0.1091701516],"iteration":91,"passed_time":0.4268012833,"remaining_time":0.9649420318},
{"learn":[0.1088752578],"iteration":92,"passed_time":0.4312867951,"remaining_time":0.959960931},
{"learn":[0.1085558483],"iteration":93,"passed_time":0.4350564783,"remaining_time":0.953421644},
{"learn":[0.1083907896],"iteration":94,"passed_time":0.4392738669,"remaining_time":0.9479067655},
{"learn":[0.1081146174],"iteration":95,"passed_time":0.443018467,"remaining_time":0.9414142423},
{"learn":[0.1079083753],"iteration":96,"passed_time":0.4470961065,"remaining_time":0.9356753569},
{"learn":[0.1076660893],"iteration":97,"passed_time":0.450873873,"remaining_time":0.9293522689},
{"learn":[0.1073928089],"iteration":98,"passed_time":0.4546757227,"remaining_time":0.9231294976},
{"learn":[0.1071243651],"iteration":99,"passed_time":0.4586896126,"remaining_time":0.9173792253},
{"learn":[0.1069366773],"iteration":100,"passed_time":0.4625369204,"remaining_time":0.9113351203},
{"learn":[0.106729213],"iteration":101,"passed_time":0.4664104779,"remaining_time":0.9053850453},
{"learn":[0.1062911318],"iteration":102,"passed_time":0.4705962834,"remaining_time":0.9000725031},
{"learn":[0.1059948129],"iteration":103,"passed_time":0.4749832125,"remaining_time":0.8951606697},
{"learn":[0.1057330905],"iteration":104,"passed_time":0.4787323959,"remaining_time":0.8890744495},
{"learn":[0.1055616958],"iteration":105,"passed_time":0.482318622,"remaining_time":0.8827340817},
{"learn":[0.1053576465],"iteration":106,"passed_time":0.4862958038,"remaining_time":0.8771503751},
{"learn":[0.1051833422],"iteration":107,"passed_time":0.4907053995,"remaining_time":0.8723651546},
{"learn":[0.1049093629],"iteration":108,"passed_time":0.4949947043,"remaining_time":0.8673760414},
{"learn":[0.104743679],"iteration":109,"passed_time":0.498732471,"remaining_time":0.8614469954},
{"learn":[0.1044841543],"iteration":110,"passed_time":0.5024785294,"remaining_time":0.8555715501},
{"learn":[0.1042620538],"iteration":111,"passed_time":0.5062314628,"remaining_time":0.8497456697},
{"learn":[0.1040973371],"iteration":112,"passed_time":0.5104188516,"remaining_time":0.8446754446},
{"learn":[0.1039227903],"iteration":113,"passed_time":0.5147656143,"remaining_time":0.8398807391},
{"learn":[0.1036964633],"iteration":114,"passed_time":0.5186582134,"remaining_time":0.8343632128},
{"learn":[0.10346593],"iteration":115,"passed_time":0.5229369349,"remaining_time":0.8294861726},
{"learn":[0.1033026982],"iteration":116,"passed_time":0.5270516991,"remaining_time":0.8243629141},
{"learn":[0.1029326512],"iteration":117,"passed_time":0.5307500912,"remaining_time":0.8186145474},
{"learn":[0.102634569],"iteration":118,"passed_time":0.5344984829,"remaining_time":0.8129766841},
{"learn":[0.1024588495],"iteration":119,"passed_time":0.5383079992,"remaining_time":0.8074619988},
{"learn":[0.1022398311],"iteration":120,"passed_time":0.5419604332,"remaining_time":0.8017431202},
{"learn":[0.1020484347],"iteration":121,"passed_time":0.5461792801,"remaining_time":0.7968845235},
{"learn":[0.1018387347],"iteration":122,"passed_time":0.5503826688,"remaining_time":0.7920140844},
{"learn":[0.1016527184],"iteration":123,"passed_time":0.5542441848,"remaining_time":0.7866691655},
{"learn":[0.1014460954],"iteration":124,"passed_time":0.5581994084,"remaining_time":0.7814791718},
{"learn":[0.1012569935],"iteration":125,"passed_time":0.5621541738,"remaining_time":0.7763081447},
{"learn":[0.1010382211],"iteration":126,"passed_time":0.5661417305,"remaining_time":0.77120094},
{"learn":[0.1008596926],"iteration":127,"passed_time":0.569971955,"remaining_time":0.7658998146},
{"learn":[0.100730097],"iteration":128,"passed_time":0.573736055,"remaining_time":0.7605338403},
{"learn":[0.1005157068],"iteration":129,"passed_time":0.5777441533,"remaining_time":0.7555115851},
{"learn":[0.1003198397],"iteration":130,"passed_time":0.5818564176,"remaining_time":0.7506391952},
{"learn":[0.1001490662],"iteration":131,"passed_time":0.5856770171,"remaining_time":0.7454071127},
{"learn":[0.0999579424],"iteration":132,"passed_time":0.5894247422,"remaining_time":0.7401047515},
{"learn":[0.09976064505],"iteration":133,"passed_time":0.5930911344,"remaining_time":0.7347248382},
{"learn":[0.09960442474],"iteration":134,"passed_time":0.5968981508,"remaining_time":0.7295421843},
{"learn":[0.09942824538],"iteration":135,"passed_time":0.6008314162,"remaining_time":0.7245320019},
{"learn":[0.09930056228],"iteration":136,"passed_time":0.6045408082,"remaining_time":0.7192711806},
{"learn":[0.0990881878],"iteration":137,"passed_time":0.6091926522,"remaining_time":0.7151392005},
{"learn":[0.09887317562],"iteration":138,"passed_time":0.6133137081,"remaining_time":0.7103849425},
{"learn":[0.0987423827],"iteration":139,"passed_time":0.6172673901,"remaining_time":0.7054484459},
{"learn":[0.09862152415],"iteration":140,"passed_time":0.6216317778,"remaining_time":0.700989026},
{"learn":[0.09847768677],"iteration":141,"passed_time":0.6253666696,"remaining_time":0.6958305196},
{"learn":[0.09827529238],"iteration":142,"passed_time":0.6291353945,"remaining_time":0.6907290694},
{"learn":[0.0980991529],"iteration":143,"passed_time":0.6331405761,"remaining_time":0.6859022908},
{"learn":[0.09797364177],"iteration":144,"passed_time":0.637258882,"remaining_time":0.6812077705},
{"learn":[0.09785169329],"iteration":145,"passed_time":0.6412033974,"remaining_time":0.6763378302},
{"learn":[0.09771589367],"iteration":146,"passed_time":0.6449967472,"remaining_time":0.671323145},
{"learn":[0.09757554959],"iteration":147,"passed_time":0.6492476772,"remaining_time":0.6667949117},
{"learn":[0.09734960731],"iteration":148,"passed_time":0.6533314,"remaining_time":0.662100949},
{"learn":[0.09715717208],"iteration":149,"passed_time":0.657293957,"remaining_time":0.657293957},
{"learn":[0.09702316128],"iteration":150,"passed_time":0.6611009733,"remaining_time":0.652344669},
{"learn":[0.09685254128],"iteration":151,"passed_time":0.665248529,"remaining_time":0.6477419888},
{"learn":[0.09670773608],"iteration":152,"passed_time":0.669008129,"remaining_time":0.6427725161},
{"learn":[0.0964917099],"iteration":153,"passed_time":0.6730524354,"remaining_time":0.6380886725},
{"learn":[0.09632252617],"iteration":154,"passed_time":0.676469121,"remaining_time":0.6328259519},
{"learn":[0.09617356066],"iteration":155,"passed_time":0.6800994718,"remaining_time":0.6277841278},
{"learn":[0.09606284315],"iteration":156,"passed_time":0.6841234033,"remaining_time":0.6231187686},
{"learn":[0.09577848702],"iteration":157,"passed_time":0.6888578718,"remaining_time":0.6191001126},
{"learn":[0.09561092234],"iteration":158,"passed_time":0.6924169731,"remaining_time":0.614030146},
{"learn":[0.0954523198],"iteration":159,"passed_time":0.6961413233,"remaining_time":0.6091236579},
{"learn":[0.09535236174],"iteration":160,"passed_time":0.7001419634,"remaining_time":0.6044703907},
{"learn":[0.0951892512],"iteration":161,"passed_time":0.703952563,"remaining_time":0.5996632944},
{"learn":[0.09508771487],"iteration":162,"passed_time":0.707797329,"remaining_time":0.5948971416},
{"learn":[0.09487370906],"iteration":163,"passed_time":0.7117329278,"remaining_time":0.5902175499},
{"learn":[0.09470895881],"iteration":164,"passed_time":0.7158786502,"remaining_time":0.5857188957},
{"learn":[0.09459098988],"iteration":165,"passed_time":0.7199623314,"remaining_time":0.5811744121},
{"learn":[0.09449710988],"iteration":166,"passed_time":0.7248127574,"remaining_time":0.5772460882},
{"learn":[0.09433683052],"iteration":167,"passed_time":0.7285953989,"remaining_time":0.5724678134},
{"learn":[0.09422018247],"iteration":168,"passed_time":0.7326317054,"remaining_time":0.5678979491},
{"learn":[0.09409978031],"iteration":169,"passed_time":0.7370668842,"remaining_time":0.563639382},
{"learn":[0.09397207373],"iteration":170,"passed_time":0.7414336468,"remaining_time":0.559327137},
{"learn":[0.0938057327],"iteration":171,"passed_time":0.7457194516,"remaining_time":0.5549540105},
{"learn":[0.09365146308],"iteration":172,"passed_time":0.7498015494,"remaining_time":0.5504323513},
{"learn":[0.09346367719],"iteration":173,"passed_time":0.7538665223,"remaining_time":0.5459033437},
{"learn":[0.09330027217],"iteration":174,"passed_time":0.7576014558,"remaining_time":0.541143897},
{"learn":[0.093093234],"iteration":175,"passed_time":0.7617063034,"remaining_time":0.5366567138},
{"learn":[0.09292189331],"iteration":176,"passed_time":0.7656090275,"remaining_time":0.532033392},
{"learn":[0.092812142],"iteration":177,"passed_time":0.7696866253,"remaining_time":0.5275380241},
{"learn":[0.09265857524],"iteration":178,"passed_time":0.7738171395,"remaining_time":0.5230830943},
{"learn":[0.09251799861],"iteration":179,"passed_time":0.7773696575,"remaining_time":0.5182464383},
{"learn":[0.09240073736],"iteration":180,"passed_time":0.7812536316,"remaining_time":0.5136418904},
{"learn":[0.09229512646],"iteration":181,"passed_time":0.7852703549,"remaining_time":0.509131329},
{"learn":[0.09212362992],"iteration":182,"passed_time":0.789057163,"remaining_time":0.5044791698},
{"learn":[0.09195805269],"iteration":183,"passed_time":0.7931054277,"remaining_time":0.5000012479},
{"learn":[0.09186875357],"iteration":184,"passed_time":0.7968700277,"remaining_time":0.4953516388},
{"learn":[0.09169026173],"iteration":185,"passed_time":0.8008392512,"remaining_time":0.4908369604},
{"learn":[0.09157071917],"iteration":186,"passed_time":0.8049517655,"remaining_time":0.4864147032},
{"learn":[0.09145769322],"iteration":187,"passed_time":0.8093185281,"remaining_time":0.4821472082},
{"learn":[0.09130067286],"iteration":188,"passed_time":0.8137117905,"remaining_time":0.4778942262},
{"learn":[0.09117757838],"iteration":189,"passed_time":0.8176584309,"remaining_time":0.4733811968},
{"learn":[0.09103910933],"iteration":190,"passed_time":0.821698279,"remaining_time":0.4689272901},
{"learn":[0.09082146962],"iteration":191,"passed_time":0.8257344605,"remaining_time":0.464475634},
{"learn":[0.09068462546],"iteration":192,"passed_time":0.8303343465,"remaining_time":0.4603408035},
{"learn":[0.09052835116],"iteration":193,"passed_time":0.8340314052,"remaining_time":0.4557078812},
{"learn":[0.09039151177],"iteration":194,"passed_time":0.8379565041,"remaining_time":0.4512073484},
{"learn":[0.09026268233],"iteration":195,"passed_time":0.8422537672,"remaining_time":0.4469101622},
{"learn":[0.09018679805],"iteration":196,"passed_time":0.8464416559,"remaining_time":0.4425557897},
{"learn":[0.09008305709],"iteration":197,"passed_time":0.8502291307,"remaining_time":0.4379968249},
{"learn":[0.08994912935],"iteration":198,"passed_time":0.8542711871,"remaining_time":0.4335748236},
{"learn":[0.08963631578],"iteration":199,"passed_time":0.8583049519,"remaining_time":0.429152476},
{"learn":[0.08950377307],"iteration":200,"passed_time":0.862098385,"remaining_time":0.4246156225},
{"learn":[0.08937056704],"iteration":201,"passed_time":0.8673804332,"remaining_time":0.420808329},
{"learn":[0.08924644793],"iteration":202,"passed_time":0.8716719879,"remaining_time":0.4165132159},
{"learn":[0.08897153964],"iteration":203,"passed_time":0.8759499178,"remaining_time":0.412211726},
{"learn":[0.08880808285],"iteration":204,"passed_time":0.8811350499,"remaining_time":0.4083308768},
{"learn":[0.08863190517],"iteration":205,"passed_time":0.8859743511,"remaining_time":0.4042795582},
{"learn":[0.08848978387],"iteration":206,"passed_time":0.8912372743,"remaining_time":0.4004109493},
{"learn":[0.08838965119],"iteration":207,"passed_time":0.8971304434,"remaining_time":0.3968076961},
{"learn":[0.08825115291],"iteration":208,"passed_time":0.9028086556,"remaining_time":0.3930889362},
{"learn":[0.08813115996],"iteration":209,"passed_time":0.9080418708,"remaining_time":0.3891608018},
{"learn":[0.08802311517],"iteration":210,"passed_time":0.913118837,"remaining_time":0.385154391},
{"learn":[0.08793058436],"iteration":211,"passed_time":0.9183121774,"remaining_time":0.3811861869},
{"learn":[0.08781535638],"iteration":212,"passed_time":0.9238816403,"remaining_time":0.3773601066},
{"learn":[0.08770135262],"iteration":213,"passed_time":0.9289460649,"remaining_time":0.3733147738},
{"learn":[0.08761818595],"iteration":214,"passed_time":0.9341759051,"remaining_time":0.3693253578},
{"learn":[0.08737738048],"iteration":215,"passed_time":0.939051956,"remaining_time":0.3651868718},
{"learn":[0.0872162823],"iteration":216,"passed_time":0.9443245042,"remaining_time":0.3611932435},
{"learn":[0.08704921465],"iteration":217,"passed_time":0.9495894692,"remaining_time":0.3571850297},
{"learn":[0.08696152709],"iteration":218,"passed_time":0.9543706457,"remaining_time":0.3529864032},
{"learn":[0.08685958588],"iteration":219,"passed_time":0.958875949,"remaining_time":0.3486821633},
{"learn":[0.08671469756],"iteration":220,"passed_time":0.9631892119,"remaining_time":0.3443074559},
{"learn":[0.08661327884],"iteration":221,"passed_time":0.9680850544,"remaining_time":0.3401379921},
{"learn":[0.08652816864],"iteration":222,"passed_time":0.9732463117,"remaining_time":0.3360536592},
{"learn":[0.08639639637],"iteration":223,"passed_time":0.9786421507,"remaining_time":0.3320393011},
{"learn":[0.08629320799],"iteration":224,"passed_time":0.9835408681,"remaining_time":0.327846956},
{"learn":[0.08612438238],"iteration":225,"passed_time":0.9894157873,"remaining_time":0.3239680012},
{"learn":[0.0859611275],"iteration":226,"passed_time":0.9954224557,"remaining_time":0.3201138294},
{"learn":[0.08580408732],"iteration":227,"passed_time":1.000258923,"remaining_time":0.315871239},
{"learn":[0.08571459048],"iteration":228,"passed_time":1.005707012,"remaining_time":0.3118130911},
{"learn":[0.08557064106],"iteration":229,"passed_time":1.012219802,"remaining_time":0.3080668963},
{"learn":[0.08546033568],"iteration":230,"passed_time":1.027190411,"remaining_time":0.3068231097},
{"learn":[0.08537352505],"iteration":231,"passed_time":1.095181583,"remaining_time":0.3210014985},
{"learn":[0.08526489355],"iteration":232,"passed_time":1.104914727,"remaining_time":0.3177222605},
{"learn":[0.08517048337],"iteration":233,"passed_time":1.115129159,"remaining_time":0.3145236088},
{"learn":[0.08506696792],"iteration":234,"passed_time":1.121155202,"remaining_time":0.310106758},
{"learn":[0.08496699493],"iteration":235,"passed_time":1.127087329,"remaining_time":0.3056508011},
{"learn":[0.08489761957],"iteration":236,"passed_time":1.132640417,"remaining_time":0.3010816298},
{"learn":[0.08482425392],"iteration":237,"passed_time":1.13796909,"remaining_time":0.2964457293},
{"learn":[0.084628389],"iteration":238,"passed_time":1.144229257,"remaining_time":0.2920417768},
{"learn":[0.08451708189],"iteration":239,"passed_time":1.14901135,"remaining_time":0.2872528374},
{"learn":[0.08437188934],"iteration":240,"passed_time":1.155061309,"remaining_time":0.2827743455},
{"learn":[0.08423147808],"iteration":241,"passed_time":1.159543446,"remaining_time":0.277907107},
{"learn":[0.08409390297],"iteration":242,"passed_time":1.164072208,"remaining_time":0.2730539747},
{"learn":[0.08402569647],"iteration":243,"passed_time":1.16823918,"remaining_time":0.2681204675},
{"learn":[0.08373145443],"iteration":244,"passed_time":1.17305619,"remaining_time":0.2633391446},
{"learn":[0.08358306778],"iteration":245,"passed_time":1.177742867,"remaining_time":0.258528922},
{"learn":[0.08343476091],"iteration":246,"passed_time":1.181823298,"remaining_time":0.2535896145},
{"learn":[0.08333761746],"iteration":247,"passed_time":1.187086763,"remaining_time":0.248905289},
{"learn":[0.08322827951],"iteration":248,"passed_time":1.191131194,"remaining_time":0.2439666302},
{"learn":[0.08310101281],"iteration":249,"passed_time":1.196064286,"remaining_time":0.2392128573},
{"learn":[0.08293457279],"iteration":250,"passed_time":1.199969219,"remaining_time":0.2342569391},
{"learn":[0.0826783062],"iteration":251,"passed_time":1.204047817,"remaining_time":0.2293424413},
{"learn":[0.08258074043],"iteration":252,"passed_time":1.208030707,"remaining_time":0.2244167716},
{"learn":[0.0824506919],"iteration":253,"passed_time":1.21230872,"remaining_time":0.2195519729},
{"learn":[0.08236256736],"iteration":254,"passed_time":1.216338401,"remaining_time":0.2146479532},
{"learn":[0.08224304258],"iteration":255,"passed_time":1.220865663,"remaining_time":0.2098362858},
{"learn":[0.08214234432],"iteration":256,"passed_time":1.224885386,"remaining_time":0.2049419129},
{"learn":[0.08206036563],"iteration":257,"passed_time":1.228979526,"remaining_time":0.2000664344},
{"learn":[0.08191278813],"iteration":258,"passed_time":1.233529329,"remaining_time":0.1952691215},
{"learn":[0.08182671235],"iteration":259,"passed_time":1.237640801,"remaining_time":0.1904062771},
{"learn":[0.08173817567],"iteration":260,"passed_time":1.241949939,"remaining_time":0.1855787266},
{"learn":[0.08151153957],"iteration":261,"passed_time":1.246512159,"remaining_time":0.1807918398},
{"learn":[0.08141912945],"iteration":262,"passed_time":1.251307335,"remaining_time":0.176039435},
{"learn":[0.08134696799],"iteration":263,"passed_time":1.255185684,"remaining_time":0.1711616842},
{"learn":[0.08124003212],"iteration":264,"passed_time":1.259246574,"remaining_time":0.1663155853},
{"learn":[0.08114108329],"iteration":265,"passed_time":1.263990959,"remaining_time":0.1615627542},
{"learn":[0.08097333569],"iteration":266,"passed_time":1.268661886,"remaining_time":0.1568009073},
{"learn":[0.08088084403],"iteration":267,"passed_time":1.272569902,"remaining_time":0.151948645},
{"learn":[0.08078751704],"iteration":268,"passed_time":1.277330162,"remaining_time":0.1472016172},
{"learn":[0.08071532952],"iteration":269,"passed_time":1.281032679,"remaining_time":0.1423369643},
{"learn":[0.08060482701],"iteration":270,"passed_time":1.286209395,"remaining_time":0.1376386437},
{"learn":[0.08045242637],"iteration":271,"passed_time":1.290817114,"remaining_time":0.1328782323},
{"learn":[0.08030140835],"iteration":272,"passed_time":1.295489333,"remaining_time":0.1281253186},
{"learn":[0.08020659656],"iteration":273,"passed_time":1.300226426,"remaining_time":0.1233791499},
{"learn":[0.08013252608],"iteration":274,"passed_time":1.304118025,"remaining_time":0.1185561841},
{"learn":[0.08007461089],"iteration":275,"passed_time":1.308403913,"remaining_time":0.1137742533},
{"learn":[0.07995785327],"iteration":276,"passed_time":1.312522969,"remaining_time":0.1089820516},
{"learn":[0.07984023116],"iteration":277,"passed_time":1.316511318,"remaining_time":0.1041843489},
{"learn":[0.07974313819],"iteration":278,"passed_time":1.319828712,"remaining_time":0.09934194609},
{"learn":[0.07965669679],"iteration":279,"passed_time":1.323492605,"remaining_time":0.09453518605},
{"learn":[0.0794797908],"iteration":280,"passed_time":1.326801874,"remaining_time":0.08971258225},
{"learn":[0.07938022042],"iteration":281,"passed_time":1.33021956,"remaining_time":0.08490763148},
{"learn":[0.07927743978],"iteration":282,"passed_time":1.334123784,"remaining_time":0.0801417114},
{"learn":[0.07912041114],"iteration":283,"passed_time":1.338133757,"remaining_time":0.07538781731},
{"learn":[0.07901606122],"iteration":284,"passed_time":1.341977565,"remaining_time":0.07063039815},
{"learn":[0.07889674289],"iteration":285,"passed_time":1.345724748,"remaining_time":0.06587463803},
{"learn":[0.07879055641],"iteration":286,"passed_time":1.349685639,"remaining_time":0.06113558642},
{"learn":[0.07868102493],"iteration":287,"passed_time":1.353579654,"remaining_time":0.05639915226},
{"learn":[0.0785767146],"iteration":288,"passed_time":1.357405004,"remaining_time":0.0516659344},
{"learn":[0.07850306735],"iteration":289,"passed_time":1.361202687,"remaining_time":0.04693802369},
{"learn":[0.078372288],"iteration":290,"passed_time":1.364905912,"remaining_time":0.04221358492},
{"learn":[0.07825193577],"iteration":291,"passed_time":1.3691948,"remaining_time":0.03751218631},
{"learn":[0.07812014889],"iteration":292,"passed_time":1.373486563,"remaining_time":0.03281367216},
{"learn":[0.07801032237],"iteration":293,"passed_time":1.377345788,"remaining_time":0.02810909771},
{"learn":[0.07787116184],"iteration":294,"passed_time":1.381506135,"remaining_time":0.02341535822},
{"learn":[0.07781188103],"iteration":295,"passed_time":1.385538775,"remaining_time":0.01872349696},
{"learn":[0.07773808548],"iteration":296,"passed_time":1.389361916,"remaining_time":0.01403395875},
{"learn":[0.07765865627],"iteration":297,"passed_time":1.394244759,"remaining_time":0.009357347373},
{"learn":[0.07752386931],"iteration":298,"passed_time":1.398754104,"remaining_time":0.00467810737},
{"learn":[0.07741987636],"iteration":299,"passed_time":1.403482155,"remaining_time":0}
]}